show_me/__init__.py
show_me/api.py
show_me/backend.py
show_me/cli.py
show_me/constants.py
show_me/db.py
show_me/utils.py
show_me-0.1.0.dist-info/LICENSE.txt
show_me-0.1.0.dist-info/METADATA
show_me-0.1.0.dist-info/RECORD
show_me-0.1.0.dist-info/WHEEL
show_me-0.1.0.dist-info/entry_points.txt
show_me-0.1.0.dist-info/top_level.txt
