Metadata-Version: 2.1
Name: show-me
Version: 0.1.0
Summary: Show me my Github contributions!
Home-page: https://github.com/TomasTomecek/show-me
Author: Tomas Tomecek
Author-email: tomas@tomecek.net
License: MIT
Keywords: github,contributions,open-source,software
Platform: UNKNOWN
Classifier: Environment :: Console
Classifier: License :: OSI Approved :: MIT License
Classifier: Programming Language :: Python
Classifier: Programming Language :: Python :: 3.6
Classifier: Programming Language :: Python :: 3.7
Requires-Python: >=3.6
Provides-Extra: testing
Requires-Dist: click
Requires-Dist: tabulate
Requires-Dist: requests
Provides-Extra: testing
Requires-Dist: pytest; extra == 'testing'
